datascience/__init__.py
datascience/formats.py
datascience/maps.py
datascience/predicates.py
datascience/tables.py
datascience/util.py
datascience/version.py
datascience/geodata/geocode_states.csv
datascience-0.18.0.dist-info/licenses/LICENSE
datascience-0.18.0.dist-info/METADATA
datascience-0.18.0.dist-info/WHEEL
datascience-0.18.0.dist-info/top_level.txt
datascience-0.18.0.dist-info/RECORD
