Metadata-Version: 2.4
Name: datascience
Version: 0.18.0
Summary: A Jupyter notebook Python library for introductory data science
Home-page: https://github.com/data-8/datascience
Download-URL: https://github.com/data-8/datascience/archive/0.18.0.zip
Author: John DeNero, David Culler, Alvin Wan, Sam Lau
Author-email: ds8-instructors@berkeley.edu
Keywords: data,tools,berkeley
Requires-Python: >=3.6
License-File: LICENSE
Requires-Dist: folium>=0.9.1
Requires-Dist: setuptools
Requires-Dist: matplotlib>=3.0.0
Requires-Dist: pandas
Requires-Dist: scipy
Requires-Dist: numpy
Requires-Dist: ipython
Requires-Dist: plotly
Requires-Dist: branca
Dynamic: author
Dynamic: author-email
Dynamic: description
Dynamic: download-url
Dynamic: home-page
Dynamic: keywords
Dynamic: license-file
Dynamic: requires-dist
Dynamic: requires-python
Dynamic: summary
